in4viz/__init__.py
in4viz/er_diagram.py
in4viz/backends/__init__.py
in4viz/backends/drawio/__init__.py
in4viz/backends/drawio/canvas.py
in4viz/backends/drawio/er_diagram.py
in4viz/backends/drawio/generator.py
in4viz/backends/drawio/rendering.py
in4viz/backends/drawio/stencil.py
in4viz/backends/svg/__init__.py
in4viz/backends/svg/canvas.py
in4viz/backends/svg/er_diagram.py
in4viz/backends/svg/rendering.py
in4viz/backends/svg/stencil.py
in4viz/core/__init__.py
in4viz/core/layout.py
in4viz/core/models.py
in4viz/core/text_metrics.py
in4viz-0.5.0.dist-info/licenses/LICENSE
in4viz-0.5.0.dist-info/METADATA
in4viz-0.5.0.dist-info/WHEEL
in4viz-0.5.0.dist-info/top_level.txt
in4viz-0.5.0.dist-info/RECORD
