Metadata-Version: 2.4
Name: in4viz
Version: 0.5.0
Summary: ER図可視化ライブラリ - SVGとdraw.io形式での出力をサポート
Author-email: Your Name <your.email@example.com>
License-Expression: MIT
Project-URL: Homepage, https://github.com/yourusername/in4viz
Project-URL: Documentation, https://github.com/yourusername/in4viz#readme
Project-URL: Repository, https://github.com/yourusername/in4viz.git
Project-URL: Bug Tracker, https://github.com/yourusername/in4viz/issues
Classifier: Development Status :: 3 - Alpha
Classifier: Intended Audience :: Developers
Classifier: Programming Language :: Python :: 3
Classifier: Programming Language :: Python :: 3.8
Classifier: Programming Language :: Python :: 3.9
Classifier: Programming Language :: Python :: 3.10
Classifier: Programming Language :: Python :: 3.11
Classifier: Programming Language :: Python :: 3.12
Classifier: Topic :: Software Development :: Libraries :: Python Modules
Requires-Python: >=3.8
License-File: LICENSE
Dynamic: license-file
